salem/__init__.py
salem/datasets.py
salem/descartes.py
salem/gis.py
salem/graphics.py
salem/sio.py
salem/utils.py
salem/version.py
salem/wrftools.py
salem/tests/__init__.py
salem/tests/test_datasets.py
salem/tests/test_gis.py
salem/tests/test_graphics.py
salem/tests/test_misc.py
Lambda_Salemx-0.0.1.dist-info/METADATA
Lambda_Salemx-0.0.1.dist-info/WHEEL
Lambda_Salemx-0.0.1.dist-info/top_level.txt
Lambda_Salemx-0.0.1.dist-info/RECORD
