Metadata-Version: 2.1
Name: Lambda-Salemx
Version: 0.0.1
Summary: Salem to aws lamda funcs
Author: v4lv3s
Author-email: gabrielalvesdealm@gmail.com
Keywords: python,aws,salem
Classifier: Development Status :: 1 - Planning
Classifier: Intended Audience :: Developers
Classifier: Programming Language :: Python :: 3
Classifier: Programming Language :: Python :: 3.8
Classifier: Programming Language :: Python :: 3.9
Classifier: Programming Language :: Python :: 3.10
Classifier: Programming Language :: Python :: 3.11
Classifier: Operating System :: Unix
Classifier: Operating System :: MacOS :: MacOS X
Classifier: Operating System :: Microsoft :: Windows
Requires-Dist: numpy
Requires-Dist: scipy
Requires-Dist: six
Requires-Dist: pyproj
Requires-Dist: joblib
Requires-Dist: netCDF4
Requires-Dist: pandas
Requires-Dist: xarray
